{"skeleton":{"hash":"Kvjt2b5DNTLkO4CODq2SVXa4l/c","spine":"3.7.90","width":139.01,"height":139,"images":"","audio":""},"bones":[{"name":"root"},{"name":"bkx","parent":"root","x":-3.98,"y":33.56},{"name":"arm","parent":"bkx","length":16.03,"rotation":47.44,"x":21.93,"y":-19.04},{"name":"body","parent":"bkx","x":-11.33,"y":-7.71},{"name":"bu","parent":"bkx","x":58.43,"y":51.93},{"name":"dian1","parent":"bkx","x":66.08,"y":-10.68},{"name":"dian2","parent":"bkx","x":56.43,"y":-2.67},{"name":"dian3","parent":"bkx","x":80.27,"y":18.99},{"name":"dian4","parent":"bkx","x":64.62,"y":71.4},{"name":"dian5","parent":"bkx","x":51.34,"y":78.68},{"name":"hand","parent":"arm","length":4.12,"rotation":2.76,"x":17.01,"y":1.8},{"name":"gan","parent":"hand","length":29.13,"rotation":-22.02,"x":4.46,"y":-0.33},{"name":"head","parent":"bkx","length":24.1,"rotation":72.57,"x":5.43,"y":28.14},{"name":"hat1","parent":"head","x":31.91,"y":0.29},{"name":"hat3","parent":"hat1","length":29.22,"rotation":-138.84,"x":-8.47,"y":-21.61},{"name":"hat4","parent":"hat1","length":26.34,"rotation":141.75,"x":-11.63,"y":26.24},{"name":"hat5","parent":"hat1","x":14.14,"y":-7.73},{"name":"kai","parent":"bkx","x":70.45,"y":31.18},{"name":"line","parent":"bkx","length":24.11,"rotation":-91.05,"x":-3.66,"y":89.53},{"name":"line2","parent":"gan","length":27.77,"rotation":-118.18,"x":28.96,"y":0.24},{"name":"yb","parent":"line2","x":34.32,"y":-0.39},{"name":"line3","parent":"yb","x":-3.49,"y":-11.33},{"name":"line4","parent":"yb","x":-3.76,"y":-14.75},{"name":"line5","parent":"yb","rotation":-127.94,"x":-4.45,"y":16.45},{"name":"line6","parent":"yb","rotation":-111.06,"x":-3.34,"y":12.12},{"name":"neck","parent":"bkx","rotation":-26.05,"x":1.82,"y":23.77},{"name":"xin","parent":"bkx","x":70.45,"y":6.25}],"slots":[{"name":"hat4","bone":"hat4","attachment":"hat4"},{"name":"head","bone":"head","attachment":"head"},{"name":"yb","bone":"yb","attachment":"yb"},{"name":"line3","bone":"line3","attachment":"line3"},{"name":"line6","bone":"line6","attachment":"line3"},{"name":"line4","bone":"line4","attachment":"line4"},{"name":"line5","bone":"line5","attachment":"line4"},{"name":"line2","bone":"line2","attachment":"line2"},{"name":"gan","bone":"gan","attachment":"gan"},{"name":"hand","bone":"hand","attachment":"hand"},{"name":"arm","bone":"arm","attachment":"arm"},{"name":"neck","bone":"neck","attachment":"neck"},{"name":"body","bone":"body","attachment":"body"},{"name":"hat2","bone":"hat5","attachment":"hat2"},{"name":"hat1","bone":"hat1","attachment":"hat1"},{"name":"hat3","bone":"hat3","attachment":"hat3"},{"name":"line","bone":"line","attachment":"line"},{"name":"dian1","bone":"dian1","attachment":"dian1"},{"name":"dian2","bone":"dian2","attachment":"dian2"},{"name":"xin","bone":"xin","attachment":"xin"},{"name":"dian3","bone":"dian3","attachment":"dian3"},{"name":"kai","bone":"kai","attachment":"kai"},{"name":"bu","bone":"bu","attachment":"bu"},{"name":"dian4","bone":"dian4","attachment":"dian4"},{"name":"dian5","bone":"dian5","attachment":"dian5"}],"skins":{"default":{"arm":{"arm":{"x":6.92,"y":-3.47,"rotation":-47.44,"width":50,"height":61}},"body":{"body":{"x":1.99,"y":2.42,"width":91,"height":71}},"bu":{"bu":{"x":-0.77,"y":0.29,"width":33,"height":32}},"dian1":{"dian1":{"x":0.09,"y":0.39,"width":8,"height":7}},"dian2":{"dian2":{"x":-0.77,"y":-0.12,"width":9,"height":8}},"dian3":{"dian3":{"x":0.39,"y":0.73,"width":7,"height":7}},"dian4":{"dian4":{"x":0.04,"y":-0.19,"width":9,"height":10}},"dian5":{"dian5":{"x":-0.17,"y":-0.47,"width":6,"height":6}},"gan":{"gan":{"x":14.17,"y":0.1,"rotation":0.42,"width":33,"height":8}},"hand":{"hand":{"x":1.45,"y":-0.16,"rotation":-50.19,"width":14,"height":13}},"hat1":{"hat1":{"x":-7.39,"y":0.35,"rotation":-72.57,"width":74,"height":49}},"hat2":{"hat2":{"x":-1.72,"y":1.72,"rotation":-72.57,"width":50,"height":37}},"hat3":{"hat3":{"x":19.64,"y":2.7,"rotation":66.27,"width":30,"height":46}},"hat4":{"hat4":{"x":17.91,"y":1.36,"rotation":145.69,"width":38,"height":32}},"head":{"head":{"x":8.8,"y":-2.73,"rotation":-72.57,"width":69,"height":67}},"kai":{"kai":{"x":-0.78,"y":-0.47,"width":27,"height":27}},"line":{"line":{"x":12.31,"y":0.56,"rotation":91.05,"width":29,"height":30}},"line2":{"line2":{"x":14.1,"y":0.03,"rotation":90,"width":3,"height":31}},"line3":{"line3":{"x":0.27,"y":1.26,"rotation":90,"width":6,"height":7}},"line4":{"line4":{"x":0.04,"y":0.18,"rotation":90,"width":5,"height":6}},"line5":{"line4":{"x":0.04,"y":0.18,"rotation":90,"width":5,"height":6}},"line6":{"line3":{"x":0.27,"y":1.26,"rotation":90,"width":6,"height":7}},"neck":{"neck":{"x":3.72,"y":-4.4,"width":56,"height":22}},"xin":{"xin":{"x":0.22,"y":0.47,"width":27,"height":27}},"yb":{"yb":{"x":0.78,"y":0.42,"rotation":90,"width":25,"height":17}}}},"animations":{"animation":{"slots":{"line3":{"color":[{"time":0,"color":"ffffff00"},{"time":0.0667,"color":"ffffffff","curve":"stepped"},{"time":0.2333,"color":"ffffffff"},{"time":0.3667,"color":"ffffff00","curve":"stepped"},{"time":0.4,"color":"ffffff00"},{"time":0.4667,"color":"ffffffff","curve":"stepped"},{"time":0.6333,"color":"ffffffff"},{"time":0.7667,"color":"ffffff00","curve":"stepped"},{"time":0.8,"color":"ffffff00"},{"time":0.8667,"color":"ffffffff","curve":"stepped"},{"time":1.0333,"color":"ffffffff"},{"time":1.1667,"color":"ffffff00","curve":"stepped"},{"time":1.2,"color":"ffffff00"},{"time":1.2667,"color":"ffffffff","curve":"stepped"},{"time":1.4333,"color":"ffffffff"},{"time":1.5667,"color":"ffffff00"}]},"line4":{"color":[{"time":0,"color":"ffffffff","curve":"stepped"},{"time":0.0333,"color":"ffffffff"},{"time":0.1667,"color":"ffffff00","curve":"stepped"},{"time":0.2,"color":"ffffff00"},{"time":0.2667,"color":"ffffffff","curve":"stepped"},{"time":0.4333,"color":"ffffffff"},{"time":0.5667,"color":"ffffff00","curve":"stepped"},{"time":0.6,"color":"ffffff00"},{"time":0.6667,"color":"ffffffff","curve":"stepped"},{"time":0.8333,"color":"ffffffff"},{"time":0.9667,"color":"ffffff00","curve":"stepped"},{"time":1,"color":"ffffff00"},{"time":1.0667,"color":"ffffffff","curve":"stepped"},{"time":1.2333,"color":"ffffffff"},{"time":1.3667,"color":"ffffff00","curve":"stepped"},{"time":1.4,"color":"ffffff00"},{"time":1.4667,"color":"ffffffff","curve":"stepped"},{"time":1.6,"color":"ffffffff"}]},"line5":{"color":[{"time":0,"color":"ffffffff","curve":"stepped"},{"time":0.0333,"color":"ffffffff"},{"time":0.1667,"color":"ffffff00","curve":"stepped"},{"time":0.2,"color":"ffffff00"},{"time":0.2667,"color":"ffffffff","curve":"stepped"},{"time":0.4333,"color":"ffffffff"},{"time":0.5667,"color":"ffffff00","curve":"stepped"},{"time":0.6,"color":"ffffff00"},{"time":0.6667,"color":"ffffffff","curve":"stepped"},{"time":0.8333,"color":"ffffffff"},{"time":0.9667,"color":"ffffff00","curve":"stepped"},{"time":1,"color":"ffffff00"},{"time":1.0667,"color":"ffffffff","curve":"stepped"},{"time":1.2333,"color":"ffffffff"},{"time":1.3667,"color":"ffffff00","curve":"stepped"},{"time":1.4,"color":"ffffff00"},{"time":1.4667,"color":"ffffffff","curve":"stepped"},{"time":1.6,"color":"ffffffff"}]},"line6":{"color":[{"time":0,"color":"ffffff00"},{"time":0.0667,"color":"ffffffff","curve":"stepped"},{"time":0.2333,"color":"ffffffff"},{"time":0.3667,"color":"ffffff00","curve":"stepped"},{"time":0.4,"color":"ffffff00"},{"time":0.4667,"color":"ffffffff","curve":"stepped"},{"time":0.6333,"color":"ffffffff"},{"time":0.7667,"color":"ffffff00","curve":"stepped"},{"time":0.8,"color":"ffffff00"},{"time":0.8667,"color":"ffffffff","curve":"stepped"},{"time":1.0333,"color":"ffffffff"},{"time":1.1667,"color":"ffffff00","curve":"stepped"},{"time":1.2,"color":"ffffff00"},{"time":1.2667,"color":"ffffffff","curve":"stepped"},{"time":1.4333,"color":"ffffffff"},{"time":1.5667,"color":"ffffff00"}]}},"bones":{"line3":{"translate":[{"time":0,"x":3.49,"y":3.64},{"time":0.3667,"x":0,"y":0},{"time":0.4,"x":3.49,"y":3.64},{"time":0.7667,"x":0,"y":0},{"time":0.8,"x":3.49,"y":3.64},{"time":1.1667,"x":0,"y":0},{"time":1.2,"x":3.49,"y":3.64},{"time":1.5667,"x":0,"y":0}],"scale":[{"time":0,"x":1.025,"y":1.025},{"time":0.3667,"x":1,"y":1},{"time":0.4,"x":1.025,"y":1.025},{"time":0.7667,"x":1,"y":1},{"time":0.8,"x":1.025,"y":1.025},{"time":1.1667,"x":1,"y":1},{"time":1.2,"x":1.025,"y":1.025},{"time":1.5667,"x":1,"y":1}]},"line4":{"translate":[{"time":0,"x":1.75,"y":3.22},{"time":0.1667,"x":0,"y":0},{"time":0.2,"x":3.86,"y":7.08},{"time":0.5667,"x":0,"y":0},{"time":0.6,"x":3.86,"y":7.08},{"time":0.9667,"x":0,"y":0},{"time":1,"x":3.86,"y":7.08},{"time":1.3667,"x":0,"y":0},{"time":1.4,"x":3.86,"y":7.08},{"time":1.6,"x":1.75,"y":3.22}],"scale":[{"time":0,"x":1.011,"y":1.011},{"time":0.1667,"x":1,"y":1},{"time":0.2,"x":1.025,"y":1.025},{"time":0.5667,"x":1,"y":1},{"time":0.6,"x":1.025,"y":1.025},{"time":0.9667,"x":1,"y":1},{"time":1,"x":1.025,"y":1.025},{"time":1.3667,"x":1,"y":1},{"time":1.4,"x":1.025,"y":1.025},{"time":1.6,"x":1.011,"y":1.011}]},"line5":{"translate":[{"time":0,"x":1.87,"y":-3.58},{"time":0.1667,"x":0,"y":0},{"time":0.2,"x":4.11,"y":-7.88},{"time":0.5667,"x":0,"y":0},{"time":0.6,"x":4.11,"y":-7.88},{"time":0.9667,"x":0,"y":0},{"time":1,"x":4.11,"y":-7.88},{"time":1.3667,"x":0,"y":0},{"time":1.4,"x":4.11,"y":-7.88},{"time":1.6,"x":1.87,"y":-3.58}],"scale":[{"time":0,"x":1.011,"y":1.011},{"time":0.1667,"x":1,"y":1},{"time":0.2,"x":1.025,"y":1.025},{"time":0.5667,"x":1,"y":1},{"time":0.6,"x":1.025,"y":1.025},{"time":0.9667,"x":1,"y":1},{"time":1,"x":1.025,"y":1.025},{"time":1.3667,"x":1,"y":1},{"time":1.4,"x":1.025,"y":1.025},{"time":1.6,"x":1.011,"y":1.011}]},"line6":{"translate":[{"time":0,"x":2.68,"y":-3.43},{"time":0.3667,"x":0,"y":0},{"time":0.4,"x":2.68,"y":-3.43},{"time":0.7667,"x":0,"y":0},{"time":0.8,"x":2.68,"y":-3.43},{"time":1.1667,"x":0,"y":0},{"time":1.2,"x":2.68,"y":-3.43},{"time":1.5667,"x":0,"y":0}],"scale":[{"time":0,"x":1.025,"y":1.025},{"time":0.3667,"x":1,"y":1},{"time":0.4,"x":1.025,"y":1.025},{"time":0.7667,"x":1,"y":1},{"time":0.8,"x":1.025,"y":1.025},{"time":1.1667,"x":1,"y":1},{"time":1.2,"x":1.025,"y":1.025},{"time":1.5667,"x":1,"y":1}]},"body":{"rotate":[{"time":0,"angle":0,"curve":[0.25,0,0.75,1]},{"time":0.4,"angle":-2.69,"curve":[0.25,0,0.75,1]},{"time":0.8,"angle":0,"curve":[0.25,0,0.75,1]},{"time":1.2,"angle":-2.69,"curve":[0.25,0,0.75,1]},{"time":1.6,"angle":0}],"translate":[{"time":0,"x":0,"y":0,"curve":[0.25,0,0.75,1]},{"time":0.4,"x":0.57,"y":0.57,"curve":[0.25,0,0.75,1]},{"time":0.8,"x":0,"y":0,"curve":[0.25,0,0.75,1]},{"time":1.2,"x":0.57,"y":0.57,"curve":[0.25,0,0.75,1]},{"time":1.6,"x":0,"y":0}]},"head":{"rotate":[{"time":0,"angle":0,"curve":[0.25,0,0.75,1]},{"time":0.4,"angle":-1.65,"curve":[0.25,0,0.75,1]},{"time":0.8,"angle":0,"curve":[0.25,0,0.75,1]},{"time":1.2,"angle":-1.65,"curve":[0.25,0,0.75,1]},{"time":1.6,"angle":0}],"translate":[{"time":0,"x":0,"y":0,"curve":[0.25,0,0.75,1]},{"time":0.4,"x":1.65,"y":-3.03,"curve":[0.25,0,0.75,1]},{"time":0.8,"x":0,"y":0,"curve":[0.25,0,0.75,1]},{"time":1.2,"x":1.65,"y":-3.03,"curve":[0.25,0,0.75,1]},{"time":1.6,"x":0,"y":0}]},"neck":{"rotate":[{"time":0,"angle":0,"curve":[0.25,0,0.75,1]},{"time":0.4,"angle":-1.13,"curve":[0.25,0,0.75,1]},{"time":0.8,"angle":0,"curve":[0.25,0,0.75,1]},{"time":1.2,"angle":-1.13,"curve":[0.25,0,0.75,1]},{"time":1.6,"angle":0}],"translate":[{"time":0,"x":0,"y":0,"curve":[0.25,0,0.75,1]},{"time":0.4,"x":1.65,"y":-1.1,"curve":[0.25,0,0.75,1]},{"time":0.8,"x":0,"y":0,"curve":[0.25,0,0.75,1]},{"time":1.2,"x":1.65,"y":-1.1,"curve":[0.25,0,0.75,1]},{"time":1.6,"x":0,"y":0}]},"hat1":{"rotate":[{"time":0,"angle":0,"curve":[0.25,0,0.75,1]},{"time":0.4,"angle":-2.32,"curve":[0.25,0,0.75,1]},{"time":0.8,"angle":0,"curve":[0.25,0,0.75,1]},{"time":1.2,"angle":-2.32,"curve":[0.25,0,0.75,1]},{"time":1.6,"angle":0}],"translate":[{"time":0,"x":0,"y":0,"curve":[0.25,0,0.75,1]},{"time":0.4,"x":0.88,"y":-1.15,"curve":[0.25,0,0.75,1]},{"time":0.8,"x":0,"y":0,"curve":[0.25,0,0.75,1]},{"time":1.2,"x":0.88,"y":-1.15,"curve":[0.25,0,0.75,1]},{"time":1.6,"x":0,"y":0}]},"hat5":{"rotate":[{"time":0,"angle":0,"curve":[0.25,0,0.75,1]},{"time":0.4,"angle":-2.32,"curve":[0.25,0,0.75,1]},{"time":0.8,"angle":0,"curve":[0.25,0,0.75,1]},{"time":1.2,"angle":-2.32,"curve":[0.25,0,0.75,1]},{"time":1.6,"angle":0}],"translate":[{"time":0,"x":0,"y":0,"curve":[0.25,0,0.75,1]},{"time":0.4,"x":-2.61,"y":-0.48,"curve":[0.25,0,0.75,1]},{"time":0.8,"x":0,"y":0,"curve":[0.25,0,0.75,1]},{"time":1.2,"x":-2.61,"y":-0.48,"curve":[0.25,0,0.75,1]},{"time":1.6,"x":0,"y":0}]},"line2":{"rotate":[{"time":0,"angle":3.78,"curve":[0.25,0,0.75,1]},{"time":0.2,"angle":-6.93,"curve":[0.25,0,0.75,1]},{"time":0.4,"angle":3.78,"curve":[0.25,0,0.75,1]},{"time":0.6,"angle":-6.93,"curve":[0.25,0,0.75,1]},{"time":0.8,"angle":3.78,"curve":[0.25,0,0.75,1]},{"time":1,"angle":-6.93,"curve":[0.25,0,0.75,1]},{"time":1.2,"angle":3.78,"curve":[0.25,0,0.75,1]},{"time":1.4,"angle":-6.93,"curve":[0.25,0,0.75,1]},{"time":1.6,"angle":3.78}]},"arm":{"rotate":[{"time":0,"angle":0,"curve":[0.25,0,0.625,0.5]},{"time":0.4,"angle":3.06,"curve":[0.375,0.5,0.75,1]},{"time":0.8,"angle":0,"curve":[0.25,0,0.75,1]},{"time":1.2,"angle":3.06,"curve":[0.375,0.5,0.75,1]},{"time":1.6,"angle":0}]},"hand":{"rotate":[{"time":0,"angle":0,"curve":[0.25,0,0.625,0.5]},{"time":0.4,"angle":-4.75,"curve":[0.375,0.5,0.75,1]},{"time":0.8,"angle":0,"curve":[0.25,0,0.75,1]},{"time":1.2,"angle":-4.75,"curve":[0.375,0.5,0.75,1]},{"time":1.6,"angle":0}]},"hat3":{"rotate":[{"time":0,"angle":0,"curve":[0.25,0,0.75,1]},{"time":0.1333,"angle":-8.43,"curve":[0.25,0,0.75,1]},{"time":0.2667,"angle":0,"curve":[0.25,0,0.75,1]},{"time":0.4,"angle":-8.43,"curve":[0.25,0,0.75,1]},{"time":0.5333,"angle":0,"curve":[0.25,0,0.75,1]},{"time":0.6667,"angle":-8.43,"curve":[0.25,0,0.75,1]},{"time":0.8,"angle":0,"curve":[0.25,0,0.75,1]},{"time":0.9333,"angle":-8.43,"curve":[0.25,0,0.75,1]},{"time":1.0667,"angle":0,"curve":[0.25,0,0.75,1]},{"time":1.2,"angle":-8.43,"curve":[0.25,0,0.75,1]},{"time":1.3333,"angle":0,"curve":[0.25,0,0.75,1]},{"time":1.4667,"angle":-8.43,"curve":[0.25,0,0.75,1]},{"time":1.6,"angle":0}]},"hat4":{"rotate":[{"time":0,"angle":0,"curve":[0.25,0,0.75,1]},{"time":0.1333,"angle":7.82,"curve":[0.25,0,0.75,1]},{"time":0.2667,"angle":0,"curve":[0.25,0,0.75,1]},{"time":0.4,"angle":7.82,"curve":[0.25,0,0.75,1]},{"time":0.5333,"angle":0,"curve":[0.25,0,0.75,1]},{"time":0.6667,"angle":7.82,"curve":[0.25,0,0.75,1]},{"time":0.8,"angle":0,"curve":[0.25,0,0.75,1]},{"time":0.9333,"angle":7.82,"curve":[0.25,0,0.75,1]},{"time":1.0667,"angle":0,"curve":[0.25,0,0.75,1]},{"time":1.2,"angle":7.82,"curve":[0.25,0,0.75,1]},{"time":1.3333,"angle":0,"curve":[0.25,0,0.75,1]},{"time":1.4667,"angle":7.82,"curve":[0.25,0,0.75,1]},{"time":1.6,"angle":0}]},"line":{"scale":[{"time":0,"x":1,"y":1},{"time":0.4,"x":0.594,"y":1},{"time":0.5333,"x":1.069,"y":1},{"time":0.6333,"x":0.814,"y":1},{"time":0.7333,"x":1.055,"y":1},{"time":0.8,"x":1,"y":1},{"time":1.2,"x":0.594,"y":1},{"time":1.3333,"x":1.069,"y":1},{"time":1.4333,"x":0.814,"y":1},{"time":1.5333,"x":1.055,"y":1},{"time":1.6,"x":1,"y":1}]},"dian5":{"translate":[{"time":0,"x":0,"y":0,"curve":[0.25,0,0.75,1]},{"time":0.4,"x":6.49,"y":0,"curve":[0.25,0,0.75,1]},{"time":0.8,"x":0,"y":0,"curve":[0.25,0,0.75,1]},{"time":1.2,"x":6.49,"y":0,"curve":[0.25,0,0.75,1]},{"time":1.6,"x":0,"y":0}],"scale":[{"time":0,"x":1,"y":1,"curve":[0.25,0,0.75,1]},{"time":0.4,"x":1.168,"y":1.168,"curve":[0.25,0,0.75,1]},{"time":0.8,"x":1,"y":1,"curve":[0.25,0,0.75,1]},{"time":1.2,"x":1.168,"y":1.168,"curve":[0.25,0,0.75,1]},{"time":1.6,"x":1,"y":1}]},"dian4":{"translate":[{"time":0,"x":1.84,"y":0,"curve":[0.382,0.57,0.735,1]},{"time":0.1333,"x":0,"y":0},{"time":0.5333,"x":6.49,"y":0,"curve":[0.25,0,0.75,1]},{"time":0.9333,"x":0,"y":0,"curve":[0.25,0,0.75,1]},{"time":1.3333,"x":6.49,"y":0,"curve":[0.243,0,0.649,0.6]},{"time":1.6,"x":1.84,"y":0}],"scale":[{"time":0,"x":1.048,"y":1.048,"curve":[0.382,0.57,0.735,1]},{"time":0.1333,"x":1,"y":1},{"time":0.5333,"x":1.168,"y":1.168,"curve":[0.25,0,0.75,1]},{"time":0.9333,"x":1,"y":1,"curve":[0.25,0,0.75,1]},{"time":1.3333,"x":1.168,"y":1.168,"curve":[0.243,0,0.649,0.6]},{"time":1.6,"x":1.048,"y":1.048}]},"bu":{"translate":[{"time":0,"x":4.65,"y":0,"curve":[0.351,0.4,0.757,1]},{"time":0.2667,"x":0,"y":0},{"time":0.6667,"x":6.49,"y":0,"curve":[0.25,0,0.75,1]},{"time":1.0667,"x":0,"y":0,"curve":[0.25,0,0.75,1]},{"time":1.4667,"x":6.49,"y":0,"curve":[0.265,0,0.618,0.43]},{"time":1.6,"x":4.65,"y":0}],"scale":[{"time":0,"x":1.121,"y":1.121,"curve":[0.351,0.4,0.757,1]},{"time":0.2667,"x":1,"y":1},{"time":0.6667,"x":1.168,"y":1.168,"curve":[0.25,0,0.75,1]},{"time":1.0667,"x":1,"y":1,"curve":[0.25,0,0.75,1]},{"time":1.4667,"x":1.168,"y":1.168,"curve":[0.265,0,0.618,0.43]},{"time":1.6,"x":1.121,"y":1.121}]},"kai":{"translate":[{"time":0,"x":6.49,"y":0,"curve":[0.25,0,0.75,1]},{"time":0.4,"x":0,"y":0},{"time":0.8,"x":6.49,"y":0,"curve":[0.25,0,0.75,1]},{"time":1.2,"x":0,"y":0,"curve":[0.25,0,0.75,1]},{"time":1.6,"x":6.49,"y":0}],"scale":[{"time":0,"x":1.168,"y":1.168,"curve":[0.25,0,0.75,1]},{"time":0.4,"x":1,"y":1},{"time":0.8,"x":1.168,"y":1.168,"curve":[0.25,0,0.75,1]},{"time":1.2,"x":1,"y":1,"curve":[0.25,0,0.75,1]},{"time":1.6,"x":1.168,"y":1.168}]},"dian3":{"translate":[{"time":0,"x":4.65,"y":0,"curve":[0.382,0.57,0.735,1]},{"time":0.1333,"x":6.49,"y":0,"curve":[0.25,0,0.75,1]},{"time":0.5333,"x":0,"y":0},{"time":0.9333,"x":6.49,"y":0,"curve":[0.25,0,0.75,1]},{"time":1.3333,"x":0,"y":0,"curve":[0.243,0,0.649,0.6]},{"time":1.6,"x":4.65,"y":0}],"scale":[{"time":0,"x":1.121,"y":1.121,"curve":[0.382,0.57,0.735,1]},{"time":0.1333,"x":1.168,"y":1.168,"curve":[0.25,0,0.75,1]},{"time":0.5333,"x":1,"y":1},{"time":0.9333,"x":1.168,"y":1.168,"curve":[0.25,0,0.75,1]},{"time":1.3333,"x":1,"y":1,"curve":[0.243,0,0.649,0.6]},{"time":1.6,"x":1.121,"y":1.121}]},"xin":{"translate":[{"time":0,"x":1.84,"y":0,"curve":[0.351,0.4,0.757,1]},{"time":0.2667,"x":6.49,"y":0,"curve":[0.25,0,0.75,1]},{"time":0.6667,"x":0,"y":0},{"time":1.0667,"x":6.49,"y":0,"curve":[0.25,0,0.75,1]},{"time":1.4667,"x":0,"y":0,"curve":[0.265,0,0.618,0.43]},{"time":1.6,"x":1.84,"y":0}],"scale":[{"time":0,"x":1.048,"y":1.048,"curve":[0.351,0.4,0.757,1]},{"time":0.2667,"x":1.168,"y":1.168,"curve":[0.25,0,0.75,1]},{"time":0.6667,"x":1,"y":1},{"time":1.0667,"x":1.168,"y":1.168,"curve":[0.25,0,0.75,1]},{"time":1.4667,"x":1,"y":1,"curve":[0.265,0,0.618,0.43]},{"time":1.6,"x":1.048,"y":1.048}]},"dian2":{"translate":[{"time":0,"x":0,"y":0,"curve":[0.25,0,0.75,1]},{"time":0.4,"x":6.49,"y":0,"curve":[0.25,0,0.75,1]},{"time":0.8,"x":0,"y":0},{"time":1.2,"x":6.49,"y":0,"curve":[0.25,0,0.75,1]},{"time":1.6,"x":0,"y":0}],"scale":[{"time":0,"x":1,"y":1,"curve":[0.25,0,0.75,1]},{"time":0.4,"x":1.168,"y":1.168,"curve":[0.25,0,0.75,1]},{"time":0.8,"x":1,"y":1},{"time":1.2,"x":1.168,"y":1.168,"curve":[0.25,0,0.75,1]},{"time":1.6,"x":1,"y":1}]},"dian1":{"translate":[{"time":0,"x":1.84,"y":0,"curve":[0.382,0.57,0.735,1]},{"time":0.1333,"x":0,"y":0,"curve":[0.25,0,0.75,1]},{"time":0.5333,"x":6.49,"y":0,"curve":[0.25,0,0.75,1]},{"time":0.9333,"x":0,"y":0},{"time":1.3333,"x":6.49,"y":0,"curve":[0.243,0,0.649,0.6]},{"time":1.6,"x":1.84,"y":0}],"scale":[{"time":0,"x":1.048,"y":1.048,"curve":[0.382,0.57,0.735,1]},{"time":0.1333,"x":1,"y":1,"curve":[0.25,0,0.75,1]},{"time":0.5333,"x":1.168,"y":1.168,"curve":[0.25,0,0.75,1]},{"time":0.9333,"x":1,"y":1},{"time":1.3333,"x":1.168,"y":1.168,"curve":[0.243,0,0.649,0.6]},{"time":1.6,"x":1.048,"y":1.048}]}}}}}